README.md
docker_compose_swarm_mode.py
setup.py
docker_compose_swarm_mode.egg-info/PKG-INFO
docker_compose_swarm_mode.egg-info/SOURCES.txt
docker_compose_swarm_mode.egg-info/dependency_links.txt
docker_compose_swarm_mode.egg-info/entry_points.txt
docker_compose_swarm_mode.egg-info/requires.txt
docker_compose_swarm_mode.egg-info/top_level.txt