Metadata-Version: 1.1
Name: docker-compose-swarm-mode
Version: 2.0.0
Summary: Drop in replacement for docker-compose that works with swarm mode introduced in Docker 1.12 (and converter to Kubernetes format).
Home-page: https://github.com/ddrozdov/docker-compose-swarm-mode
Author: Dmitry Drozdov
Author-email: UNKNOWN
License: MIT
Download-URL: https://github.com/ddrozdov/docker-compose-swarm-mode/tarball/2.0.0
Keywords: docker,docker-compose,swarm
Platform: UNKNOWN
Classifier: License :: OSI Approved :: MIT License
Classifier: Programming Language :: Python :: 2.7
Classifier: Programming Language :: Python :: 3.4
